README.rst
setup.py
src/automaton.py
src/python_automaton.egg-info/PKG-INFO
src/python_automaton.egg-info/SOURCES.txt
src/python_automaton.egg-info/dependency_links.txt
src/python_automaton.egg-info/requires.txt
src/python_automaton.egg-info/top_level.txt