Metadata-Version: 1.1
Name: python-automaton
Version: 1.2.1
Summary: Minimal finite-state machines
Home-page: https://github.com/nazavode/automaton
Author: Federico Ficarelli
Author-email: federico.ficarelli@gmail.com
License: UNKNOWN
Keywords: automata automaton statemachine
Platform: UNKNOWN
Classifier: Development Status :: 5 - Production/Stable
Classifier: Intended Audience :: Developers
Classifier: Topic :: Software Development :: Libraries
Classifier: License :: OSI Approved :: Apache Software License
Classifier: Programming Language :: Python :: 3.4
Classifier: Programming Language :: Python :: 3.5
Classifier: Programming Language :: Python :: 3.6
Classifier: Operating System :: OS Independent
